ez_docs/__init__.py
ez_docs/main.py
ez_docs/cmd/__init__.py
ez_docs/cmd/about.txt
ez_docs/cmd/architecture.txt
ez_docs/cmd/help.txt
ez_docs/cmd/list.txt
ez_docs/modules/__init__.py
ez_docs/modules/data_cleaning.py
ez_docs/modules/doc_generation.py
ez_docs/modules/usable.py
ez_docs-1.1.0.dist-info/LICENSE
ez_docs-1.1.0.dist-info/METADATA
ez_docs-1.1.0.dist-info/WHEEL
ez_docs-1.1.0.dist-info/entry_points.txt
ez_docs-1.1.0.dist-info/top_level.txt
ez_docs-1.1.0.dist-info/RECORD
