Metadata-Version: 2.1
Name: ez-docs
Version: 1.1.0
Summary: A python package to quick doc generation
Home-page: https://github.com/fga-eps-mds/2022-2-ez-docs
Author: 
Author-email: ezdocsteam@gmail.com
License: MIT
Keywords: ez_docs,ez-docs
Classifier: Programming Language :: Python :: 3
Classifier: License :: OSI Approved :: MIT License
Classifier: Operating System :: OS Independent
License-File: LICENSE
Requires-Dist: mdpdf (==0.0.18)
Requires-Dist: pandas (==1.5.2)
Requires-Dist: pytest (==7.2.0)
Requires-Dist: bumpversion (==0.6.0)
Requires-Dist: openpyxl (==3.1.0)
Requires-Dist: lxml (==4.9.2)
